zander/__init__.py
zander/generator.py
zander/init.py
zander/install.py
zander/monitor.py
zander/renderer.py
zander/scripts.py
zander/template_engine.py
zander/data/init_template/data/_config.yml
zander/exception/__init__.py
zander/exception/package_config.py
zander/model/__init__.py
zander/model/package_config.py
zander/model/template.py
zander/provider/__init__.py
zander/provider/template.py
zander/template/__init__.py
zander/template/render.py
zander/utils/__init__.py
zander/utils/cli_utils.py
zander/utils/cmd_utils.py
zander/utils/io_utils.py
zander/utils/package_config_utils.py
zander/utils/template_utils.py
zander/utils/transform_utils.py
zander/utils/yaml_utils.py
zander-0.0.14.dist-info/DESCRIPTION.rst
zander-0.0.14.dist-info/METADATA
zander-0.0.14.dist-info/RECORD
zander-0.0.14.dist-info/WHEEL
zander-0.0.14.dist-info/entry_points.txt
zander-0.0.14.dist-info/metadata.json
zander-0.0.14.dist-info/top_level.txt
