Metadata-Version: 2.0
Name: zander
Version: 0.0.14
Summary: Code Generator
Home-page: https://github.com/thongdong7/code-gen
Author: Thong Dong
Author-email: thongdong7@gmail.com
License: UNKNOWN
Platform: UNKNOWN
Requires-Dist: click (==6.6)
Requires-Dist: jinja2 (==2.8)
Requires-Dist: pyfunctional
Requires-Dist: pyyaml
Requires-Dist: tornado (==4.4.2)
